hefesto/__init__.py
hefesto/__main__.py
hefesto/__version__.py
hefesto/analyzers/__init__.py
hefesto/analyzers/best_practices.py
hefesto/analyzers/code_smells.py
hefesto/analyzers/complexity.py
hefesto/analyzers/security.py
hefesto/analyzers/devops/__init__.py
hefesto/analyzers/devops/dockerfile_analyzer.py
hefesto/analyzers/devops/groovy_jenkins_analyzer.py
hefesto/analyzers/devops/json_analyzer.py
hefesto/analyzers/devops/makefile_analyzer.py
hefesto/analyzers/devops/powershell_analyzer.py
hefesto/analyzers/devops/shell_analyzer.py
hefesto/analyzers/devops/sql_analyzer.py
hefesto/analyzers/devops/terraform_analyzer.py
hefesto/analyzers/devops/toml_analyzer.py
hefesto/analyzers/devops/yaml_analyzer.py
hefesto/api/__init__.py
hefesto/api/dependencies.py
hefesto/api/main.py
hefesto/api/middleware.py
hefesto/api/types.py
hefesto/api/routers/__init__.py
hefesto/api/routers/analysis.py
hefesto/api/routers/findings.py
hefesto/api/routers/health.py
hefesto/api/schemas/__init__.py
hefesto/api/schemas/analysis.py
hefesto/api/schemas/common.py
hefesto/api/schemas/findings.py
hefesto/api/schemas/health.py
hefesto/api/services/__init__.py
hefesto/api/services/analysis_service.py
hefesto/api/services/bigquery_service.py
hefesto/cli/__init__.py
hefesto/cli/main.py
hefesto/config/__init__.py
hefesto/config/config_manager.py
hefesto/config/settings.py
hefesto/config/stripe_config.py
hefesto/core/__init__.py
hefesto/core/analysis_models.py
hefesto/core/analyzer_engine.py
hefesto/core/language_detector.py
hefesto/core/models.py
hefesto/core/ast/__init__.py
hefesto/core/ast/generic_ast.py
hefesto/core/languages/__init__.py
hefesto/core/languages/registry.py
hefesto/core/languages/specs.py
hefesto/core/parsers/__init__.py
hefesto/core/parsers/base_parser.py
hefesto/core/parsers/parser_factory.py
hefesto/core/parsers/python_parser.py
hefesto/core/parsers/treesitter_parser.py
hefesto/core/providers/__init__.py
hefesto/core/providers/base.py
hefesto/core/providers/registry.py
hefesto_ai-4.5.5.dist-info/licenses/LICENSE
hefesto_ai-4.5.5.dist-info/METADATA
hefesto_ai-4.5.5.dist-info/WHEEL
hefesto_ai-4.5.5.dist-info/entry_points.txt
hefesto_ai-4.5.5.dist-info/top_level.txt
hefesto_ai-4.5.5.dist-info/RECORD
