Metadata-Version: 2.4
Name: hefesto-ai
Version: 4.5.5
Summary: AI-Powered Code Quality Guardian with Gemini integration
Home-page: https://github.com/artvepa80/Agents-Hefesto
Author: Narapa LLC
Author-email: Narapa LLC <sales@narapallc.com>
Maintainer-email: Narapa LLC <sales@narapallc.com>
License: Dual License (MIT + Commercial)
Project-URL: Homepage, https://github.com/artvepa80/Agents-Hefesto
Project-URL: Documentation, https://github.com/artvepa80/Agents-Hefesto#readme
Project-URL: Repository, https://github.com/artvepa80/Agents-Hefesto
Project-URL: Issues, https://github.com/artvepa80/Agents-Hefesto/issues
Project-URL: Pro License, https://buy.stripe.com/hefesto-pro
Keywords: ai,code-quality,refactoring,security,gemini,llm,devtools
Platform: any
Classifier: Development Status :: 4 - Beta
Classifier: Intended Audience :: Developers
Classifier: Topic :: Software Development :: Quality Assurance
Classifier: Topic :: Software Development :: Code Generators
Classifier: License :: OSI Approved :: MIT License
Classifier: Programming Language :: Python :: 3
Classifier: Programming Language :: Python :: 3.10
Classifier: Programming Language :: Python :: 3.11
Classifier: Programming Language :: Python :: 3.12
Classifier: Operating System :: OS Independent
Classifier: Typing :: Typed
Requires-Python: >=3.8
License-File: LICENSE
Requires-Dist: fastapi<1.0.0,>=0.104.0
Requires-Dist: uvicorn[standard]<1.0.0,>=0.24.0
Requires-Dist: pydantic<3.0.0,>=2.5.0
Requires-Dist: click<9.0.0,>=8.0.0
Requires-Dist: google-cloud-bigquery<4.0.0,>=3.10.0
Requires-Dist: google-generativeai>=0.3.0
Requires-Dist: httpx<1.0.0,>=0.25.0
Requires-Dist: python-dateutil<3.0.0,>=2.8.2
Requires-Dist: radon<7.0.0,>=6.0.1
Requires-Dist: bandit<2.0.0,>=1.7.5
Requires-Dist: vulture<3.0.0,>=2.10
Requires-Dist: pylint<4.0.0,>=3.0.0
Requires-Dist: mccabe<1.0.0,>=0.7.0
Requires-Dist: jinja2<4.0.0,>=3.1.2
Requires-Dist: tree-sitter<1.0.0,>=0.20.0
Provides-Extra: pro
Requires-Dist: sentence-transformers<3.0.0,>=2.2.2; extra == "pro"
Requires-Dist: torch<3.0.0,>=2.0.1; extra == "pro"
Requires-Dist: numpy<2.0.0,>=1.24.0; extra == "pro"
Provides-Extra: omega
Requires-Dist: sentence-transformers<3.0.0,>=2.2.2; extra == "omega"
Requires-Dist: torch<3.0.0,>=2.0.1; extra == "omega"
Requires-Dist: numpy<2.0.0,>=1.24.0; extra == "omega"
Requires-Dist: google-cloud-bigquery<4.0.0,>=3.10.0; extra == "omega"
Requires-Dist: google-cloud-pubsub<3.0.0,>=2.18.0; extra == "omega"
Requires-Dist: pyyaml<7.0,>=6.0; extra == "omega"
Provides-Extra: dev
Requires-Dist: pytest<8.0.0,>=7.4.0; extra == "dev"
Requires-Dist: pytest-cov<5.0.0,>=4.1.0; extra == "dev"
Requires-Dist: pytest-asyncio<1.0.0,>=0.21.0; extra == "dev"
Requires-Dist: black>=23.0.0; extra == "dev"
Requires-Dist: isort>=5.12.0; extra == "dev"
Requires-Dist: flake8>=6.1.0; extra == "dev"
Requires-Dist: mypy>=1.7.0; extra == "dev"
Provides-Extra: all
Requires-Dist: sentence-transformers<3.0.0,>=2.2.2; extra == "all"
Requires-Dist: torch<3.0.0,>=2.0.1; extra == "all"
Requires-Dist: numpy<2.0.0,>=1.24.0; extra == "all"
Requires-Dist: google-cloud-bigquery<4.0.0,>=3.10.0; extra == "all"
Requires-Dist: google-cloud-pubsub<3.0.0,>=2.18.0; extra == "all"
Requires-Dist: pyyaml<7.0,>=6.0; extra == "all"
Requires-Dist: tree-sitter<1.0.0,>=0.20.0; extra == "all"
Dynamic: author
Dynamic: home-page
Dynamic: license-file
Dynamic: platform
Dynamic: requires-python
